json_manager/__init__.py
json_manager/buffered_cmd2.py
json_manager/db_console.py
json_manager/json_console.py
json_manager/main.py
json_manager_cli-0.1.7.dist-info/entry_points.txt
json_manager_cli-0.1.7.dist-info/METADATA
json_manager_cli-0.1.7.dist-info/WHEEL
json_manager_cli-0.1.7.dist-info/RECORD
