Metadata-Version: 2.1
Name: json-manager-cli
Version: 0.1.7
Summary: 
Author: sean
Author-email: sean.li@vectorindex.cloud
Requires-Python: >=3.10,<4.0
Classifier: Programming Language :: Python :: 3
Classifier: Programming Language :: Python :: 3.10
Classifier: Programming Language :: Python :: 3.11
Classifier: Programming Language :: Python :: 3.12
Requires-Dist: cmd2 (>=2.5.11,<3.0.0)
Requires-Dist: python-dotenv (>=1.0.1,<2.0.0)
Requires-Dist: requests (>=2.32.3,<3.0.0)
Requires-Dist: thefuzz (>=0.22.1,<0.23.0)
Requires-Dist: tinydb (>=4.8.2,<5.0.0)
